dagster_snowflake_pandas/__init__.py
dagster_snowflake_pandas/snowflake_pandas_type_handler.py
dagster_snowflake_pandas/version.py
dagster_snowflake_pandas-1.0.5.dist-info/LICENSE
dagster_snowflake_pandas-1.0.5.dist-info/METADATA
dagster_snowflake_pandas-1.0.5.dist-info/WHEEL
dagster_snowflake_pandas-1.0.5.dist-info/top_level.txt
dagster_snowflake_pandas-1.0.5.dist-info/RECORD
